{
 "root": "חמם",
 "members": [
  {
   "lemma": "לְחַמֵּם",
   "pos": "Verb",
   "binyan": "PI'EL",
   "meaning": "to heat, to warm up"
  },
  {
   "lemma": "חֹם",
   "pos": "Noun",
   "binyan": "",
   "meaning": "heat, warmth"
  },
  {
   "lemma": "חַם",
   "pos": "Adjective",
   "binyan": "",
   "meaning": "hot, warm"
  },
  {
   "lemma": "חַמָּה",
   "pos": "Noun",
   "binyan": "",
   "meaning": "sun (lit.)"
  },
  {
   "lemma": "חָמִים",
   "pos": "Adjective",
   "binyan": "",
   "meaning": "warm; cosy, pleasant"
  },
  {
   "lemma": "חִמּוּם",
   "pos": "Noun",
   "binyan": "",
   "meaning": "heating, warming; stimulation"
  },
  {
   "lemma": "חֲמָמָה",
   "pos": "Noun",
   "binyan": "",
   "meaning": "greenhouse, hothouse"
  },
  {
   "lemma": "הִתְחַמְּמוּת",
   "pos": "Noun",
   "binyan": "",
   "meaning": "heating, warming up, becoming hot"
  }
 ]
}