{
 "root": "חנה",
 "members": [
  {
   "lemma": "לַחֲנוֹת",
   "pos": "Verb",
   "binyan": "PA'AL",
   "meaning": "to park; to camp"
  },
  {
   "lemma": "לְהַחֲנוֹת",
   "pos": "Verb",
   "binyan": "HIF'IL",
   "meaning": "to park (a car)"
  },
  {
   "lemma": "חֲנוּת",
   "pos": "Noun",
   "binyan": "",
   "meaning": "shop, store"
  },
  {
   "lemma": "מַחֲנֶה",
   "pos": "Noun",
   "binyan": "",
   "meaning": "camp"
  },
  {
   "lemma": "חֲנָיָה",
   "pos": "Noun",
   "binyan": "",
   "meaning": "parking"
  },
  {
   "lemma": "חֲנִיָּה",
   "pos": "Noun",
   "binyan": "",
   "meaning": "parking"
  },
  {
   "lemma": "תַּחֲנָה",
   "pos": "Noun",
   "binyan": "",
   "meaning": "station, stop (train, autobus, etc.)"
  }
 ]
}