{
 "root": "שנה",
 "members": [
  {
   "lemma": "לִשְׁנוֹת",
   "pos": "Verb",
   "binyan": "PA'AL",
   "meaning": "to repeat, to review"
  },
  {
   "lemma": "לְשַׁנּוֹת",
   "pos": "Verb",
   "binyan": "PI'EL",
   "meaning": "to change (something)"
  },
  {
   "lemma": "לְהִשְׁתַּנּוֹת",
   "pos": "Verb",
   "binyan": "HITPA'EL",
   "meaning": "to change (oneself)"
  },
  {
   "lemma": "שֹׁנִי",
   "pos": "Noun",
   "binyan": "",
   "meaning": "difference"
  },
  {
   "lemma": "שׁוֹנֶה",
   "pos": "Adjective",
   "binyan": "",
   "meaning": "different; separate; various, diverse"
  },
  {
   "lemma": "שִׁנּוּי",
   "pos": "Noun",
   "binyan": "",
   "meaning": "change"
  },
  {
   "lemma": "מִשְׁנָה",
   "pos": "Noun",
   "binyan": "",
   "meaning": "Mishna (Judaism); doctrine, theory"
  },
  {
   "lemma": "מְשֻׁנֶּה",
   "pos": "Adjective",
   "binyan": "",
   "meaning": "strange, weird, unusual"
  },
  {
   "lemma": "הִשְׁתַּנּוּת",
   "pos": "Noun",
   "binyan": "",
   "meaning": "change, changing"
  }
 ]
}